Metadata-Version: 2.1
Name: seqmats
Version: 0.1.3
Summary: A small python package to make handling genomic sequences and manipulations a bit quicker.
Home-page: https://github.com/shuds13/pyexample
Author: Nicolas Lynn
Author-email: nicolasalynn@gmail.com
License: Free for non-commercial use
Classifier: Development Status :: 3 - Alpha
Classifier: Intended Audience :: Science/Research
Classifier: License :: Free for non-commercial use
Classifier: Operating System :: POSIX :: Linux
Classifier: Operating System :: MacOS
Classifier: Programming Language :: Python :: 3.9
Requires-Dist: numpy
